empyre/__init__.py
empyre/fields/__init__.py
empyre/fields/field.py
empyre/fields/shapes.py
empyre/fields/vectors.py
empyre/io/__init__.py
empyre/io/io_field.py
empyre/io/field_plugins/__init__.py
empyre/io/field_plugins/llg.py
empyre/io/field_plugins/numpy.py
empyre/io/field_plugins/ovf.py
empyre/io/field_plugins/tec.py
empyre/io/field_plugins/text.py
empyre/io/field_plugins/vtk.py
empyre/models/__init__.py
empyre/reconstruct/__init__.py
empyre/utils/__init__.py
empyre/utils/misc.py
empyre/utils/quaternion.py
empyre/vis/__init__.py
empyre/vis/colors.py
empyre/vis/decorators.py
empyre/vis/plot2d.py
empyre/vis/plot3d.py
empyre/vis/tools.py
empyre/vis/mplstyles/empyre-image.mplstyle
empyre/vis/mplstyles/empyre-plot.mplstyle
empyre/vis/mplstyles/empyre-save.mplstyle
empyre-0.3.5.dist-info/METADATA
empyre-0.3.5.dist-info/WHEEL
empyre-0.3.5.dist-info/licenses/LICENSE
empyre-0.3.5.dist-info/RECORD
