Metadata-Version: 2.4
Name: empyre
Version: 0.3.5
Summary: Electron Microscopy Python Reconstruction
Project-URL: Homepage, https://iffgit.fz-juelich.de/empyre/empyre
Author-email: Jan Caron <j.caron@fz-juelich.de>
License-Expression: GPL-3.0-or-later
License-File: LICENSE
Keywords: Electron Microscopy,Inverse Problem Solving,Model-based Reconstrution
Classifier: Development Status :: 3 - Alpha
Classifier: Intended Audience :: Developers
Classifier: Intended Audience :: Science/Research
Classifier: License :: OSI Approved :: GNU General Public License v3 (GPLv3)
Classifier: Operating System :: OS Independent
Classifier: Programming Language :: Python :: 3.6
Classifier: Programming Language :: Python :: 3.7
Classifier: Programming Language :: Python :: 3.8
Classifier: Programming Language :: Python :: 3.9
Classifier: Programming Language :: Python :: 3.10
Classifier: Topic :: Scientific/Engineering
Requires-Python: >=3.6
Requires-Dist: matplotlib>=3.2
Requires-Dist: numpy>=1.17
Requires-Dist: pillow
Requires-Dist: scikit-image
Requires-Dist: scipy
Requires-Dist: tqdm
Provides-Extra: 3d
Requires-Dist: mayavi>=4.7; extra == '3d'
Provides-Extra: all
Requires-Dist: cmocean; extra == 'all'
Requires-Dist: pyfftw; extra == 'all'
Provides-Extra: colors
Requires-Dist: cmocean; extra == 'colors'
Provides-Extra: docs
Requires-Dist: nbsphinx; extra == 'docs'
Requires-Dist: nbsphinx-link; extra == 'docs'
Requires-Dist: numpydoc; extra == 'docs'
Requires-Dist: pandoc; extra == 'docs'
Requires-Dist: sphinx; extra == 'docs'
Requires-Dist: sphinx-rtd-theme; extra == 'docs'
Provides-Extra: fftw
Requires-Dist: pyfftw; extra == 'fftw'
Provides-Extra: io
Requires-Dist: hyperspy; extra == 'io'
Requires-Dist: tvtk; extra == 'io'
Provides-Extra: tests
Requires-Dist: coverage; extra == 'tests'
Requires-Dist: pyroma; extra == 'tests'
Requires-Dist: pytest; extra == 'tests'
Requires-Dist: pytest-cov; extra == 'tests'
Requires-Dist: pytest-flake8; extra == 'tests'
Requires-Dist: pytest-runner; extra == 'tests'
